nbdime/__init__.py
nbdime/__main__.py
nbdime/_version.py
nbdime/args.py
nbdime/config.py
nbdime/diff_format.py
nbdime/diff_format.schema.json
nbdime/diff_utils.py
nbdime/gitfiles.py
nbdime/ignorables.py
nbdime/log.py
nbdime/merge_format.schema.json
nbdime/nbdiffapp.py
nbdime/nbmergeapp.py
nbdime/nbpatchapp.py
nbdime/nbshowapp.py
nbdime/patching.py
nbdime/prettyprint.py
nbdime/profiling.py
nbdime/utils.py
nbdime/diffing/__init__.py
nbdime/diffing/config.py
nbdime/diffing/directorydiff.py
nbdime/diffing/generic.py
nbdime/diffing/lcs.py
nbdime/diffing/notebooks.py
nbdime/diffing/seq_bruteforce.py
nbdime/diffing/seq_difflib.py
nbdime/diffing/seq_myers.py
nbdime/diffing/sequences.py
nbdime/diffing/snakes.py
nbdime/merging/__init__.py
nbdime/merging/autoresolve.py
nbdime/merging/chunks.py
nbdime/merging/decisions.py
nbdime/merging/generic.py
nbdime/merging/notebooks.py
nbdime/merging/strategies.py
nbdime/notebook_ext/index.js
nbdime/notebook_ext/nbdime.yaml
nbdime/tests/__init__.py
nbdime/tests/conftest.py
nbdime/tests/test_apply_merge.py
nbdime/tests/test_args.py
nbdime/tests/test_autoresolve.py
nbdime/tests/test_cli_apps.py
nbdime/tests/test_decision_tools.py
nbdime/tests/test_diff.py
nbdime/tests/test_diff_format.py
nbdime/tests/test_diff_gitrefs.py
nbdime/tests/test_diff_json_conversion.py
nbdime/tests/test_diff_performance.py
nbdime/tests/test_diff_sequence.py
nbdime/tests/test_diff_sequence_bruteforce.py
nbdime/tests/test_diff_sequence_difflib.py
nbdime/tests/test_directory_differ.py
nbdime/tests/test_git_diffdriver.py
nbdime/tests/test_git_filter_integration.py
nbdime/tests/test_hg_differ.py
nbdime/tests/test_js_artifacts_installed.py
nbdime/tests/test_merge.py
nbdime/tests/test_merge_format.py
nbdime/tests/test_merge_notebooks.py
nbdime/tests/test_merge_notebooks_inline.py
nbdime/tests/test_myers.py
nbdime/tests/test_notebook_diff.py
nbdime/tests/test_package.py
nbdime/tests/test_patch.py
nbdime/tests/test_prettyprint.py
nbdime/tests/test_server_extension.py
nbdime-4.0.0.dist-info/METADATA
nbdime-4.0.0.dist-info/WHEEL
nbdime-4.0.0.dist-info/entry_points.txt
nbdime-4.0.0.dist-info/licenses/LICENSE.md
nbdime-4.0.0.dist-info/RECORD
