Metadata-Version: 2.1
Name: nbdime
Version: 4.0.0
Summary: Diff and merge of Jupyter Notebooks
Project-URL: Homepage, https://nbdime.readthedocs.io
Project-URL: Bug Tracker, https://github.com/jupyter/nbdime/issues
Project-URL: Source, https://github.com/jupyter/nbdime
Author-email: Jupyter Development Team <jupyter@googlegroups.com>
License: # Licensing terms
License-File: LICENSE.md
Keywords: Interactive,Interpreter,Shell,Web
Classifier: Framework :: Jupyter
Classifier: Framework :: Jupyter :: JupyterLab
Classifier: Framework :: Jupyter :: JupyterLab :: 4
Classifier: Framework :: Jupyter :: JupyterLab :: Extensions
Classifier: Framework :: Jupyter :: JupyterLab :: Extensions :: Prebuilt
Classifier: Intended Audience :: Developers
Classifier: Intended Audience :: Science/Research
Classifier: Intended Audience :: System Administrators
Classifier: License :: OSI Approved :: BSD License
Classifier: Programming Language :: Python
Classifier: Programming Language :: Python :: 3
Classifier: Programming Language :: Python :: 3.6
Classifier: Programming Language :: Python :: 3.7
Classifier: Programming Language :: Python :: 3.8
Classifier: Programming Language :: Python :: 3.9
Classifier: Programming Language :: Python :: 3.10
Classifier: Programming Language :: Python :: 3.11
Requires-Python: >=3.6
Requires-Dist: colorama
Requires-Dist: gitpython!=2.1.4,!=2.1.5,!=2.1.6
Requires-Dist: jinja2>=2.9
Requires-Dist: jupyter-server
Requires-Dist: jupyter-server-mathjax>=0.2.2
Requires-Dist: nbformat
Requires-Dist: pygments
Requires-Dist: requests
Requires-Dist: tornado
Provides-Extra: docs
Requires-Dist: recommonmark; extra == 'docs'
Requires-Dist: sphinx; extra == 'docs'
Requires-Dist: sphinx-rtd-theme; extra == 'docs'
Provides-Extra: test
Requires-Dist: jsonschema; extra == 'test'
Requires-Dist: jupyter-server[test]; extra == 'test'
Requires-Dist: mock; extra == 'test'
Requires-Dist: notebook; extra == 'test'
Requires-Dist: pytest-cov; extra == 'test'
Requires-Dist: pytest-timeout; extra == 'test'
Requires-Dist: pytest-tornado; extra == 'test'
Requires-Dist: pytest>=6.0; extra == 'test'
Requires-Dist: requests; extra == 'test'
Requires-Dist: tabulate; extra == 'test'
